{"layout.qmd":[],"elements.qmd":[],"styling.qmd":[],"slidecraft-colors-fonts/index.qmd":[],"theme.qmd":[],"slidecraft-colors-fonts/index.md":[],"slidecraft-plot-backgrounds/index.qmd":[],"slidecraft-scss-uses/index.qmd":[],"examples/tip-1.qmd":[],"miscellaneous.qmd":[],"slidecraft-scss-loops/index.qmd":[],"scss.qmd":[],"summary.qmd":[],"slidecraft-asciicast/index.qmd":[],"slidecraft-layout/index.qmd":[],"slidecraft-code-output/index.md":["knuth84","each","mixin","include","each","mixin","for"],"slidecraft-scss-themes/index.qmd":[],"fragments.qmd":[],"references.qmd":[],"slidecraft-theme-variants/index.md":[],"asciicast.qmd":[],"manual-code.qmd":[],"10-minute.qmd":[],"slidecraft-plot-sizing/index.qmd":[],"fonts.qmd":[],"slidecraft-7-tips-and-tricks/index.qmd":[],"letterbox.qmd":[],"intro.qmd":["knuth84"],"slidecraft-code-output/index.qmd":[],"index.qmd":["knuth84"],"colors.qmd":[],"slidecraft-theme-variants/index.qmd":[]}
